sclsd/__init__.py
sclsd/_version.py
sclsd/py.typed
sclsd/analysis/__init__.py
sclsd/analysis/metrics.py
sclsd/core/__init__.py
sclsd/core/config.py
sclsd/core/model.py
sclsd/core/networks.py
sclsd/plotting/__init__.py
sclsd/plotting/components.py
sclsd/plotting/streamlines.py
sclsd/plotting/walks.py
sclsd/preprocessing/__init__.py
sclsd/preprocessing/data.py
sclsd/preprocessing/prior.py
sclsd/train/__init__.py
sclsd/train/trainer.py
sclsd/train/walks.py
sclsd/utils/__init__.py
sclsd/utils/io.py
sclsd/utils/seed.py
sclsd-0.2.0.dist-info/METADATA
sclsd-0.2.0.dist-info/WHEEL
sclsd-0.2.0.dist-info/licenses/LICENSE
sclsd-0.2.0.dist-info/RECORD
