Metadata-Version: 2.4
Name: sclsd
Version: 0.2.0
Summary: Latent State Dynamics (LSD) for single-cell trajectory inference via neural ODE gradient flow
Project-URL: Homepage, https://github.com/csglab/sclsd
Project-URL: Documentation, https://csglab.github.io/sclsd
Project-URL: Repository, https://github.com/csglab/sclsd
Project-URL: Issues, https://github.com/csglab/sclsd/issues
Author: LSD Development Team
License-Expression: MIT
License-File: LICENSE
Keywords: Waddington-landscape,cell-differentiation,deep-learning,neural-ode,pyro,single-cell,trajectory-inference,variational-inference
Classifier: Development Status :: 4 - Beta
Classifier: Intended Audience :: Science/Research
Classifier: License :: OSI Approved :: MIT License
Classifier: Operating System :: OS Independent
Classifier: Programming Language :: Python :: 3
Classifier: Programming Language :: Python :: 3.9
Classifier: Programming Language :: Python :: 3.10
Classifier: Programming Language :: Python :: 3.11
Classifier: Topic :: Scientific/Engineering :: Artificial Intelligence
Classifier: Topic :: Scientific/Engineering :: Bio-Informatics
Requires-Python: >=3.9
Requires-Dist: anndata>=0.9.0
Requires-Dist: cellrank>=2.0.0
Requires-Dist: leidenalg
Requires-Dist: matplotlib>=3.7.0
Requires-Dist: numpy<2.0.0,>=1.23.0
Requires-Dist: pandas>=2.0.0
Requires-Dist: pyro-ppl>=1.8.0
Requires-Dist: scanpy>=1.9.0
Requires-Dist: scikit-learn>=1.3.0
Requires-Dist: scipy>=1.10.0
Requires-Dist: seaborn>=0.12.0
Requires-Dist: torch>=2.0.0
Requires-Dist: torchdiffeq>=0.2.0
Requires-Dist: tqdm>=4.60.0
Requires-Dist: umap-learn>=0.5.0
Provides-Extra: all
Requires-Dist: black>=23.0.0; extra == 'all'
Requires-Dist: furo>=2024.0.0; extra == 'all'
Requires-Dist: mypy>=1.0.0; extra == 'all'
Requires-Dist: myst-parser>=2.0.0; extra == 'all'
Requires-Dist: nbsphinx>=0.9.0; extra == 'all'
Requires-Dist: pre-commit>=3.0.0; extra == 'all'
Requires-Dist: pytest-cov>=4.0.0; extra == 'all'
Requires-Dist: pytest>=7.0.0; extra == 'all'
Requires-Dist: ruff>=0.1.0; extra == 'all'
Requires-Dist: sphinx-autodoc-typehints>=1.25.0; extra == 'all'
Requires-Dist: sphinx-copybutton>=0.5.0; extra == 'all'
Requires-Dist: sphinx>=7.0.0; extra == 'all'
Provides-Extra: dev
Requires-Dist: black>=23.0.0; extra == 'dev'
Requires-Dist: mypy>=1.0.0; extra == 'dev'
Requires-Dist: pre-commit>=3.0.0; extra == 'dev'
Requires-Dist: pytest-cov>=4.0.0; extra == 'dev'
Requires-Dist: pytest>=7.0.0; extra == 'dev'
Requires-Dist: ruff>=0.1.0; extra == 'dev'
Provides-Extra: docs
Requires-Dist: furo>=2024.0.0; extra == 'docs'
Requires-Dist: myst-parser>=2.0.0; extra == 'docs'
Requires-Dist: nbsphinx>=0.9.0; extra == 'docs'
Requires-Dist: sphinx-autodoc-typehints>=1.25.0; extra == 'docs'
Requires-Dist: sphinx-copybutton>=0.5.0; extra == 'docs'
Requires-Dist: sphinx>=7.0.0; extra == 'docs'
